[
    {
        "name":"EIFFEL TOWER",
        "description":"The Eiffel Tower is a wrought-iron lattice tower on the Champ de Mars in Paris.",
        "price":"150",
        "img":"https://i.ibb.co/X8r4HXL/package-1.png"
    },
    {
        "name":"TOWER BRIDGE",
        "description":"Tower Bridge is a Grade I listed combined bascule and suspension bridge in London.",
        "price":"120",
        "img":"https://i.ibb.co/RBxM4Sj/Tower-Bridge-London-Flat-Vector-Icon-Historical-Landmarks-Related-Illustration-Light-Flat-Style-Blue.jpg"
    },
    {
        "name":"SIDNEY OPERA HOUSE",
        "description":"The Sydney Opera House is a multi-venue performing arts centre in Sydney.",
        "price":"180",
        "img":"https://i.ibb.co/4t9LtdT/package-3.jpg"
    },
    {
        "name":"LONDON EYE",
        "description":"The London Eye, or the Millennium Wheel, is a cantilevered observation.",
        "price":"170",
        "img":"https://i.ibb.co/t2cT4sN/package-4.jpg"
    },
    {
        "name":"THE PANTHEON",
        "description":"The Pantheon from Greek Πάνθειον Pantheion, is a former Roman temple.",
        "price":"190",
        "img":"https://i.ibb.co/y4t9q0W/package-6.jpg"
    },
    {
        "name":"SPACE NEEDLE",
        "description":"The Space Needle is an observation tower in Seattle, Washington, United States.",
        "price":"140",
        "img":"https://i.ibb.co/R96cwfJ/package-7.jpg"
    }
]










